{    
    "name": "Cadian Shock Troops",
    "ppm":6,
    "move":6,
    "tough": 3,
    "save": 5,
    "hp":1,
    "lead": 7,
    "oc": 2,
    "keywords": [
        "Infantry",
        "Battleline",
        "Grenades",
        "Regiment",
        "Platoon",
        "Cadian"
    ],
    "core_rules": ["Secure Objectives"],
    "faction_rules": [],
    "unit_rules": [],
    "range_weapons": [
        "lasgun",
        "laspistol"
    ],
    "melee_weapons": [
        "chainsword",
        "close_combat_weapon"
    ],
    "wargear":[
        "vox_caster"
    ],
    "composition":[
        "9-18 Shock Troopers",
        "1-2 Shock Trooper Sergeant (1 per 9 Shock Troopers)"
    ],
    "models_min": 10,
    "models_max": 20,
    "default_gear":[
        "lasgun"
    ],
    "replacement_gear":{
    },
    "additional_gear": [
        "Shock Trooper Sergeants have their lasgun replaced with a laspistol",
        "Every 10th model (not a Sergeant) is equipped with a Vox-Caster"
    ]
}
